codc/__init__.py
codc/constants.py
codc/encoder.py
codc/frame.py
codc/lib.py
codc/processed_odc.h
codc/reader.py
pyodc/__init__.py
pyodc/codec.py
pyodc/constants.py
pyodc/encoder.py
pyodc/frame.py
pyodc/reader.py
pyodc/stream.py
pyodc-1.0.3.dist-info/LICENSE
pyodc-1.0.3.dist-info/METADATA
pyodc-1.0.3.dist-info/WHEEL
pyodc-1.0.3.dist-info/top_level.txt
pyodc-1.0.3.dist-info/zip-safe
pyodc-1.0.3.dist-info/RECORD
